toolcore/__init__.py
toolcore/exceptions.py
toolcore/func.py
toolcore/json_type.py
toolcore/parsers/__init__.py
toolcore/parsers/abc.py
toolcore/parsers/atomic_type_parser.py
toolcore/parsers/bool_parser.py
toolcore/parsers/dataclass_parser.py
toolcore/parsers/default.py
toolcore/parsers/dict_parser.py
toolcore/parsers/enum_parser.py
toolcore/parsers/float_parser.py
toolcore/parsers/int_parser.py
toolcore/parsers/list_parser.py
toolcore/parsers/none_parser.py
toolcore/parsers/str_parser.py
toolcore/parsers/union_parser.py
toolcore/py.typed
toolcore-0.1.0.dist-info/LICENSE
toolcore-0.1.0.dist-info/METADATA
toolcore-0.1.0.dist-info/WHEEL
toolcore-0.1.0.dist-info/RECORD
